xhttpy/__init__.py
xhttpy/core.py
xhttpy-0.1.0.dist-info/METADATA
xhttpy-0.1.0.dist-info/WHEEL
xhttpy-0.1.0.dist-info/top_level.txt
xhttpy-0.1.0.dist-info/RECORD
