Metadata-Version: 2.4
Name: xhttpy
Version: 0.1.0
Summary: Unified sync/async HTTP client supporting httpx and aiohttp backends.
Home-page: https://github.com/hscspring/xhttpy.git
Author: Yam
Author-email: haoshaochun@gmail.com
Classifier: Programming Language :: Python :: 3
Classifier: License :: OSI Approved :: MIT License
Classifier: Operating System :: OS Independent
Requires-Python: >=3.7
Requires-Dist: httpx
Requires-Dist: aiohttp
Dynamic: author
Dynamic: author-email
Dynamic: classifier
Dynamic: description
Dynamic: description-content-type
Dynamic: home-page
Dynamic: requires-dist
Dynamic: requires-python
Dynamic: summary
